damage_calculator/__init__.py
damage_calculator/calculator.py
damage_calculator-0.4.0.dist-info/LICENSE
damage_calculator-0.4.0.dist-info/METADATA
damage_calculator-0.4.0.dist-info/WHEEL
damage_calculator-0.4.0.dist-info/entry_points.txt
damage_calculator-0.4.0.dist-info/top_level.txt
damage_calculator-0.4.0.dist-info/RECORD
